sefirat_haomer/__init__.py
sefirat_haomer/omer_calendar.py
sefirat_haomer/omer_date.py
sefirat_haomer/omer_day.py
sefirat_haomer/py.typed
sefirat_haomer/texts/__init__.py
sefirat_haomer/texts/english_text.py
sefirat_haomer/texts/hebrew_text.py
sefirat_haomer/texts/phonetic_hebrew_text.py
sefirat_haomer/texts/text.py
sefirat_haomer-1.0.0.dist-info/LICENSE
sefirat_haomer-1.0.0.dist-info/METADATA
sefirat_haomer-1.0.0.dist-info/WHEEL
sefirat_haomer-1.0.0.dist-info/RECORD
