Metadata-Version: 2.1
Name: sefirat-haomer
Version: 1.0.0
Summary: A library for calculating the days of Sefirat HaOmer.
Home-page: https://github.com/abrahammurciano/python-sefirat-haomer
License: GPLv3
Author: Abaham Murciano
Author-email: abrahammurciano@gmail.com
Requires-Python: >=3.10,<4.0
Classifier: License :: Other/Proprietary License
Classifier: Programming Language :: Python :: 3
Classifier: Programming Language :: Python :: 3.10
Classifier: Programming Language :: Python :: 3.11
Requires-Dist: pyluach (>=2.2.0,<3.0.0)
Project-URL: Documentation, https://abrahammurciano.github.io/python-sefirat-haomer/sefirat-haomer
Project-URL: Repository, https://github.com/abrahammurciano/python-sefirat-haomer
